transaction_mcp/__init__.py
transaction_mcp/__main__.py
transaction_mcp/server.py
transaction_mcp/prompts/__init__.py
transaction_mcp/prompts/decode_workflow.py
transaction_mcp/prompts/gas_workflow.py
transaction_mcp/prompts/token_workflow.py
transaction_mcp/prompts/transfer_workflow.py
transaction_mcp/resources/__init__.py
transaction_mcp/resources/chain_ids.py
transaction_mcp/resources/eip1559.py
transaction_mcp/resources/gas_guide.py
transaction_mcp/resources/transaction_types.py
transaction_mcp/tools/__init__.py
transaction_mcp/tools/building.py
transaction_mcp/tools/decoding.py
transaction_mcp/tools/encoding.py
transaction_mcp/tools/gas.py
transaction_mcp/tools/signing.py
transaction_mcp_server-1.0.0.dist-info/METADATA
transaction_mcp_server-1.0.0.dist-info/WHEEL
transaction_mcp_server-1.0.0.dist-info/entry_points.txt
transaction_mcp_server-1.0.0.dist-info/RECORD
